{
  "description": {
    "keyword_list": ["promotion","promotions","deals","deal","coupon", "coupons", "offer", "offers","off","men","women","boys","girls","children","kids","infants","christmas","noël","reduce","reduction","save"]
  },
   "coupon_code": {
    "keyword_list": ["coupon code","promo code","coupon codes","promo codes"]
  },
  "terms": {
    "keyword_list": ["terms","conditions","terms and conditions","terms & conditions","valid","valid until","valid till","apply","exclusions","starting at","$","lkr","%","€"]
  },
  "expiry": {
    "keyword_list": ["expires","expiry","expire","expiration","expired","december","dec","nov","2020","november"]
  }
}